<?xml version="1.0" encoding="euc-kr"?>
<words><word><text>¶Ù¾î¿À´Ù</text><definition>Come running</definition><date-of-entry>0</date-of-entry><reading-level>0</reading-level><writing-level>0</writing-level><id>-2313187644926081917</id><test><date>Fri Dec 03 10:23:10 PST 2004</date><name>basic_writing.test</name><grade>fail</grade></test><test><date>Fri Dec 03 10:25:01 PST 2004</date><name>basic_writing.test</name><grade>pass</grade></test><test><date>Fri Dec 03 10:26:50 PST 2004</date><name>basic_writing.test</name><grade>pass</grade></test><test><date>Sun Jan 30 13:27:14 PST 2005</date><name>level 0 reading.test</name><grade>pass</grade></test><test><date>Mon Mar 21 11:23:04 PST 2005</date><name>level 1 reading.test</name><grade>pass</grade></test><test><date>Mon Oct 03 10:56:34 KST 2005</date><name>level 2 writing.test</name><grade>fail</grade></test><test><date>Mon Jan 09 03:09:55 KST 2006</date><name>level 2 reading.test</name><grade>fail</grade></test><test><date>Thu May 04 23:21:12 KST 2006</date><name>level 1 reading.test</name><grade>fail</grade></test><test><date>Tue Aug 01 20:25:50 KST 2006</date><name>level 1 writing.test</name><grade>pass</grade></test><test><date>Thu Nov 02 14:40:42 KST 2006</date><name>level 2 reading.test</name><grade>fail</grade></test><test><date>Wed Oct 10 04:33:42 KST 2007</date><name>level 2 writing.test</name><grade>fail</grade></test><test><date>Fri Oct 26 21:01:05 KST 2007</date><name>level 1 writing.test</name><grade>fail</grade></test><test><date>Tue Nov 06 19:21:20 KST 2007</date><name>level 0 writing.test</name><grade>pass</grade></test><test><date>Wed Nov 07 01:08:48 KST 2007</date><name>level 3 reading.test</name><grade>fail</grade></test><test><date>Sat Nov 24 19:09:31 KST 2007</date><name>level 1 writing.test</name><grade>pass</grade></test><test><date>Thu Jan 24 14:07:30 KST 2008</date><name>level 2 writing.test</name><grade>fail</grade></test><test><date>Mon Mar 03 23:36:08 KST 2008</date><name>level 3 reading.test</name><grade>fail</grade></test><test><date>Tue May 20 19:07:50 KST 2008</date><name>level 3 writing.test</name><grade>pass</grade></test><test><date>Wed Apr 01 10:41:44 KST 2009</date><name>level 3 writing.test</name><grade>pass</grade></test><test><date>Tue Jun 09 14:05:32 KST 2009</date><name>level 3 reading.test</name><grade>fail</grade></test><test><date>Mon Apr 12 23:15:49 KST 2010</date><name>level 3 writing.test</name><grade>pass</grade></test><test><date>Mon May 17 11:59:37 KST 2010</date><name>level 3 reading.test</name><grade>fail</grade></test><test><date>Mon Sep 20 15:32:45 KST 2010</date><name>level 2 reading.test</name><grade>fail</grade></test><test><date>Thu May 26 16:33:43 KST 2011</date><name>level 3 writing.test</name><grade>pass</grade></test></word><word><text>¶Ù¾î¿À´Ù</text><definition>Come running</definition><date-of-entry>0</date-of-entry><reading-level>0</reading-level><writing-level>0</writing-level><id>-2313187644926081917</id><test><date>Fri Dec 03 10:23:10 PST 2004</date><name>basic_writing.test</name><grade>fail</grade></test><test><date>Fri Dec 03 10:25:01 PST 2004</date><name>basic_writing.test</name><grade>pass</grade></test><test><date>Fri Dec 03 10:26:50 PST 2004</date><name>basic_writing.test</name><grade>pass</grade></test><test><date>Sun Jan 30 13:27:14 PST 2005</date><name>level 0 reading.test</name><grade>pass</grade></test><test><date>Mon Mar 21 11:23:04 PST 2005</date><name>level 1 reading.test</name><grade>pass</grade></test><test><date>Mon Oct 03 10:56:34 KST 2005</date><name>level 2 writing.test</name><grade>fail</grade></test><test><date>Mon Jan 09 03:09:55 KST 2006</date><name>level 2 reading.test</name><grade>fail</grade></test><test><date>Thu May 04 23:21:12 KST 2006</date><name>level 1 reading.test</name><grade>fail</grade></test><test><date>Tue Aug 01 20:25:50 KST 2006</date><name>level 1 writing.test</name><grade>pass</grade></test><test><date>Thu Nov 02 14:40:42 KST 2006</date><name>level 2 reading.test</name><grade>fail</grade></test><test><date>Wed Oct 10 04:33:42 KST 2007</date><name>level 2 writing.test</name><grade>fail</grade></test><test><date>Fri Oct 26 21:01:05 KST 2007</date><name>level 1 writing.test</name><grade>fail</grade></test><test><date>Tue Nov 06 19:21:20 KST 2007</date><name>level 0 writing.test</name><grade>pass</grade></test><test><date>Wed Nov 07 01:08:48 KST 2007</date><name>level 3 reading.test</name><grade>fail</grade></test><test><date>Sat Nov 24 19:09:31 KST 2007</date><name>level 1 writing.test</name><grade>pass</grade></test><test><date>Thu Jan 24 14:07:30 KST 2008</date><name>level 2 writing.test</name><grade>fail</grade></test><test><date>Mon Mar 03 23:36:08 KST 2008</date><name>level 3 reading.test</name><grade>fail</grade></test><test><date>Tue May 20 19:07:50 KST 2008</date><name>level 3 writing.test</name><grade>pass</grade></test><test><date>Wed Apr 01 10:41:44 KST 2009</date><name>level 3 writing.test</name><grade>pass</grade></test><test><date>Tue Jun 09 14:05:32 KST 2009</date><name>level 3 reading.test</name><grade>fail</grade></test><test><date>Mon Apr 12 23:15:49 KST 2010</date><name>level 3 writing.test</name><grade>pass</grade></test><test><date>Mon May 17 11:59:37 KST 2010</date><name>level 3 reading.test</name><grade>fail</grade></test><test><date>Mon Sep 20 15:32:45 KST 2010</date><name>level 2 reading.test</name><grade>fail</grade></test><test><date>Thu May 26 16:33:43 KST 2011</date><name>level 3 writing.test</name><grade>pass</grade></test></word></words>
