<?xml version="1.0" encoding="euc-kr"?>
<words><word><text>

ÇÞºµ</text><definition>sun rays</definition><date-of-entry>1215670469826</date-of-entry><reading-level>0</reading-level><writing-level>0</writing-level><id>-2763693288547496233</id><test><date>Fri Jul 25 13:24:58 KST 2008</date><name>level 0 writing.test</name><grade>fail</grade></test><test><date>Thu Aug 07 15:35:48 KST 2008</date><name>level 0 reading.test</name><grade>fail</grade></test><test><date>Fri Aug 15 06:14:23 KST 2008</date><name>level 1 writing.test</name><grade>pass</grade></test><test><date>Mon Aug 25 14:19:17 KST 2008</date><name>level 1 reading.test</name><grade>fail</grade></test><test><date>Thu Sep 25 18:15:17 KST 2008</date><name>level 2 writing.test</name><grade>fail</grade></test><test><date>Tue Oct 07 18:05:38 KST 2008</date><name>level 2 reading.test</name><grade>pass</grade></test><test><date>Tue Oct 28 17:55:59 KST 2008</date><name>level 1 writing.test</name><grade>fail</grade></test><test><date>Mon Dec 08 15:38:57 KST 2008</date><name>level 2 writing.test</name><grade>fail</grade></test><test><date>Sun Aug 09 11:33:40 KST 2009</date><name>level 3 reading.test</name><grade>pass</grade></test><test><date>Thu Oct 22 15:09:04 KST 2009</date><name>level 3 writing.test</name><grade>fail</grade></test><test><date>Sat Dec 26 17:08:02 KST 2009</date><name>level 2 writing.test</name><grade>fail</grade></test><test><date>Fri Feb 12 16:56:07 KST 2010</date><name>level 1 writing.test</name><grade>fail</grade></test><test><date>Sun May 02 16:45:30 KST 2010</date><name>level 0 writing.test</name><grade>pass</grade></test><test><date>Fri May 21 10:55:15 KST 2010</date><name>level 3 reading.test</name><grade>pass</grade></test><test><date>Mon Jul 12 16:17:54 KST 2010</date><name>level 1 writing.test</name><grade>fail</grade></test><test><date>Mon Sep 20 10:39:53 KST 2010</date><name>level 0 writing.test</name><grade>pass</grade></test><test><date>Wed Oct 20 14:08:03 KST 2010</date><name>level 1 writing.test</name><grade>pass</grade></test><test><date>Wed Dec 01 14:37:02 KST 2010</date><name>level 2 writing.test</name><grade>pass</grade></test></word><word><text>

ÇÞºµ</text><definition>sun rays</definition><date-of-entry>1215670469826</date-of-entry><reading-level>0</reading-level><writing-level>0</writing-level><id>-2763693288547496233</id><test><date>Fri Jul 25 13:24:58 KST 2008</date><name>level 0 writing.test</name><grade>fail</grade></test><test><date>Thu Aug 07 15:35:48 KST 2008</date><name>level 0 reading.test</name><grade>fail</grade></test><test><date>Fri Aug 15 06:14:23 KST 2008</date><name>level 1 writing.test</name><grade>pass</grade></test><test><date>Mon Aug 25 14:19:17 KST 2008</date><name>level 1 reading.test</name><grade>fail</grade></test><test><date>Thu Sep 25 18:15:17 KST 2008</date><name>level 2 writing.test</name><grade>fail</grade></test><test><date>Tue Oct 07 18:05:38 KST 2008</date><name>level 2 reading.test</name><grade>pass</grade></test><test><date>Tue Oct 28 17:55:59 KST 2008</date><name>level 1 writing.test</name><grade>fail</grade></test><test><date>Mon Dec 08 15:38:57 KST 2008</date><name>level 2 writing.test</name><grade>fail</grade></test><test><date>Sun Aug 09 11:33:40 KST 2009</date><name>level 3 reading.test</name><grade>pass</grade></test><test><date>Thu Oct 22 15:09:04 KST 2009</date><name>level 3 writing.test</name><grade>fail</grade></test><test><date>Sat Dec 26 17:08:02 KST 2009</date><name>level 2 writing.test</name><grade>fail</grade></test><test><date>Fri Feb 12 16:56:07 KST 2010</date><name>level 1 writing.test</name><grade>fail</grade></test><test><date>Sun May 02 16:45:30 KST 2010</date><name>level 0 writing.test</name><grade>pass</grade></test><test><date>Fri May 21 10:55:15 KST 2010</date><name>level 3 reading.test</name><grade>pass</grade></test><test><date>Mon Jul 12 16:17:54 KST 2010</date><name>level 1 writing.test</name><grade>fail</grade></test><test><date>Mon Sep 20 10:39:53 KST 2010</date><name>level 0 writing.test</name><grade>pass</grade></test><test><date>Wed Oct 20 14:08:03 KST 2010</date><name>level 1 writing.test</name><grade>pass</grade></test><test><date>Wed Dec 01 14:37:02 KST 2010</date><name>level 2 writing.test</name><grade>pass</grade></test></word></words>
