<?xml version="1.0" encoding="euc-kr"?>
<words><word><text>
유감스럽다</text><definition>to feel regret</definition><date-of-entry>1202528368005</date-of-entry><reading-level>0</reading-level><writing-level>0</writing-level><id>-4549818828375259188</id><test><date>Sat Mar 01 13:19:13 KST 2008</date><name>level 0 reading.test</name><grade>fail</grade></test><test><date>Tue Mar 04 22:40:24 KST 2008</date><name>level 0 writing.test</name><grade>fail</grade></test><test><date>Tue Aug 26 03:22:36 KST 2008</date><name>level 1 reading.test</name><grade>fail</grade></test><test><date>Thu Nov 20 05:52:27 KST 2008</date><name>level 0 reading.test</name><grade>fail</grade></test><test><date>Mon Dec 15 19:17:02 KST 2008</date><name>level 0 writing.test</name><grade>fail</grade></test><test><date>Fri May 29 16:21:29 KST 2009</date><name>level 0 writing.test</name><grade>pass</grade></test><test><date>Wed Jun 10 09:46:44 KST 2009</date><name>level 0 reading.test</name><grade>fail</grade></test><test><date>Mon Oct 19 11:23:52 KST 2009</date><name>level 0 reading.test</name><grade>pass</grade></test><test><date>Mon Dec 14 12:30:16 KST 2009</date><name>level 1 writing.test</name><grade>fail</grade></test><test><date>Wed Dec 16 10:54:28 KST 2009</date><name>level 1 reading.test</name><grade>fail</grade></test><test><date>Tue Jan 26 11:57:55 KST 2010</date><name>level 0 writing.test</name><grade>pass</grade></test><test><date>Thu Feb 04 17:31:17 KST 2010</date><name>level 0 reading.test</name><grade>fail</grade></test><test><date>Sun May 02 10:59:12 KST 2010</date><name>level 0 reading.test</name><grade>pass</grade></test><test><date>Sun May 02 11:30:19 KST 2010</date><name>level 1 writing.test</name><grade>pass</grade></test><test><date>Mon Jul 12 11:26:30 KST 2010</date><name>level 1 reading.test</name><grade>fail</grade></test><test><date>Tue Aug 31 09:27:05 KST 2010</date><name>level 2 writing.test</name><grade>pass</grade></test><test><date>Thu Sep 02 11:57:12 KST 2010</date><name>level 0 reading.test</name><grade>pass</grade></test><test><date>Fri Oct 22 11:26:12 KST 2010</date><name>level 1 reading.test</name><grade>pass</grade></test><test><date>Wed Dec 01 16:01:32 KST 2010</date><name>level 2 reading.test</name><grade>fail</grade></test><test><date>Mon Mar 21 16:32:53 KST 2011</date><name>level 1 reading.test</name><grade>fail</grade></test><test><date>Mon Apr 18 14:52:40 KST 2011</date><name>level 0 reading.test</name><grade>fail</grade></test><test><date>Tue May 24 22:06:58 KST 2011</date><name>level 0 reading.test</name><grade>pass</grade></test><test><date>Sat Sep 17 18:15:05 KST 2011</date><name>level 1 reading.test</name><grade>fail</grade></test><test><date>Thu Oct 06 19:10:00 KST 2011</date><name>level 0 reading.test</name><grade>fail</grade></test><test><date>Wed Oct 12 16:22:53 KST 2011</date><name>level 0 reading.test</name><grade>pass</grade></test><test><date>Tue Jan 10 14:36:07 KST 2012</date><name>level 1 reading.test</name><grade>pass</grade></test></word><word><text>
유감스럽다</text><definition>to feel regret</definition><date-of-entry>1202528368005</date-of-entry><reading-level>0</reading-level><writing-level>0</writing-level><id>-4549818828375259188</id><test><date>Sat Mar 01 13:19:13 KST 2008</date><name>level 0 reading.test</name><grade>fail</grade></test><test><date>Tue Mar 04 22:40:24 KST 2008</date><name>level 0 writing.test</name><grade>fail</grade></test><test><date>Tue Aug 26 03:22:36 KST 2008</date><name>level 1 reading.test</name><grade>fail</grade></test><test><date>Thu Nov 20 05:52:27 KST 2008</date><name>level 0 reading.test</name><grade>fail</grade></test><test><date>Mon Dec 15 19:17:02 KST 2008</date><name>level 0 writing.test</name><grade>fail</grade></test><test><date>Fri May 29 16:21:29 KST 2009</date><name>level 0 writing.test</name><grade>pass</grade></test><test><date>Wed Jun 10 09:46:44 KST 2009</date><name>level 0 reading.test</name><grade>fail</grade></test><test><date>Mon Oct 19 11:23:52 KST 2009</date><name>level 0 reading.test</name><grade>pass</grade></test><test><date>Mon Dec 14 12:30:16 KST 2009</date><name>level 1 writing.test</name><grade>fail</grade></test><test><date>Wed Dec 16 10:54:28 KST 2009</date><name>level 1 reading.test</name><grade>fail</grade></test><test><date>Tue Jan 26 11:57:55 KST 2010</date><name>level 0 writing.test</name><grade>pass</grade></test><test><date>Thu Feb 04 17:31:17 KST 2010</date><name>level 0 reading.test</name><grade>fail</grade></test><test><date>Sun May 02 10:59:12 KST 2010</date><name>level 0 reading.test</name><grade>pass</grade></test><test><date>Sun May 02 11:30:19 KST 2010</date><name>level 1 writing.test</name><grade>pass</grade></test><test><date>Mon Jul 12 11:26:30 KST 2010</date><name>level 1 reading.test</name><grade>fail</grade></test><test><date>Tue Aug 31 09:27:05 KST 2010</date><name>level 2 writing.test</name><grade>pass</grade></test><test><date>Thu Sep 02 11:57:12 KST 2010</date><name>level 0 reading.test</name><grade>pass</grade></test><test><date>Fri Oct 22 11:26:12 KST 2010</date><name>level 1 reading.test</name><grade>pass</grade></test><test><date>Wed Dec 01 16:01:32 KST 2010</date><name>level 2 reading.test</name><grade>fail</grade></test><test><date>Mon Mar 21 16:32:53 KST 2011</date><name>level 1 reading.test</name><grade>fail</grade></test><test><date>Mon Apr 18 14:52:40 KST 2011</date><name>level 0 reading.test</name><grade>fail</grade></test><test><date>Tue May 24 22:06:58 KST 2011</date><name>level 0 reading.test</name><grade>pass</grade></test><test><date>Sat Sep 17 18:15:05 KST 2011</date><name>level 1 reading.test</name><grade>fail</grade></test><test><date>Thu Oct 06 19:10:00 KST 2011</date><name>level 0 reading.test</name><grade>fail</grade></test><test><date>Wed Oct 12 16:22:53 KST 2011</date><name>level 0 reading.test</name><grade>pass</grade></test><test><date>Tue Jan 10 14:36:07 KST 2012</date><name>level 1 reading.test</name><grade>pass</grade></test></word></words>
