<?xml version="1.0" encoding="euc-kr"?>
<words><word><text>¿¬ÈÞ</text><definition>Long holiday</definition><date-of-entry>0</date-of-entry><reading-level>0</reading-level><writing-level>0</writing-level><id>3930872808523095697</id><test><date>Thu Dec 02 23:55:22 PST 2004</date><name>basic_writing.test</name><grade>pass</grade></test><test><date>Sat Jan 08 20:14:07 PST 2005</date><name>level 1 reading.test</name><grade>fail</grade></test><test><date>Sat Jan 29 19:05:26 PST 2005</date><name>level 2 writing.test</name><grade>pass</grade></test><test><date>Sun Jan 30 14:21:27 PST 2005</date><name>level 0 reading.test</name><grade>fail</grade></test><test><date>Sun Jan 30 14:23:45 PST 2005</date><name>level 0 reading.test</name><grade>pass</grade></test><test><date>Fri May 12 21:26:47 KST 2006</date><name>level 1 reading.test</name><grade>fail</grade></test><test><date>Wed Aug 02 16:07:43 KST 2006</date><name>level 0 reading.test</name><grade>fail</grade></test><test><date>Wed Aug 23 12:35:41 KST 2006</date><name>level 0 reading.test</name><grade>fail</grade></test><test><date>Fri Oct 26 21:18:28 KST 2007</date><name>level 3 writing.test</name><grade>fail</grade></test><test><date>Mon Dec 10 18:05:43 KST 2007</date><name>level 1 reading.test</name><grade>fail</grade></test><test><date>Sat Dec 29 12:09:42 KST 2007</date><name>level 2 writing.test</name><grade>fail</grade></test><test><date>Fri Apr 11 21:44:15 KST 2008</date><name>level 2 reading.test</name><grade>pass</grade></test><test><date>Fri Nov 07 09:17:35 KST 2008</date><name>level 3 writing.test</name><grade>fail</grade></test><test><date>Fri Dec 26 15:22:30 KST 2008</date><name>level 2 writing.test</name><grade>fail</grade></test><test><date>Fri Jul 03 16:35:11 KST 2009</date><name>level 1 writing.test</name><grade>fail</grade></test><test><date>Thu Aug 20 11:36:09 KST 2009</date><name>level 0 writing.test</name><grade>fail</grade></test><test><date>Tue Sep 01 16:58:54 KST 2009</date><name>level 3 reading.test</name><grade>pass</grade></test><test><date>Wed Sep 16 17:05:44 KST 2009</date><name>level 0 writing.test</name><grade>pass</grade></test><test><date>Tue Dec 15 15:07:23 KST 2009</date><name>level 1 writing.test</name><grade>fail</grade></test><test><date>Tue Jan 26 12:28:28 KST 2010</date><name>level 0 writing.test</name><grade>pass</grade></test><test><date>Sun May 02 14:23:14 KST 2010</date><name>level 1 writing.test</name><grade>fail</grade></test><test><date>Tue May 04 13:51:02 KST 2010</date><name>level 0 writing.test</name><grade>fail</grade></test><test><date>Mon May 17 16:20:26 KST 2010</date><name>level 0 writing.test</name><grade>pass</grade></test><test><date>Tue Jun 01 09:54:51 KST 2010</date><name>level 3 reading.test</name><grade>fail</grade></test><test><date>Tue Aug 03 11:49:51 KST 2010</date><name>level 1 writing.test</name><grade>fail</grade></test><test><date>Mon Oct 18 08:41:11 KST 2010</date><name>level 2 reading.test</name><grade>fail</grade></test><test><date>Mon Oct 18 15:55:55 KST 2010</date><name>level 1 writing.test</name><grade>pass</grade></test><test><date>Tue Nov 30 10:56:20 KST 2010</date><name>level 1 reading.test</name><grade>pass</grade></test><test><date>Wed Dec 01 11:17:12 KST 2010</date><name>level 2 writing.test</name><grade>pass</grade></test><test><date>Thu May 12 16:13:56 KST 2011</date><name>level 2 reading.test</name><grade>fail</grade></test><test><date>Mon Jul 25 13:02:47 KST 2011</date><name>level 1 reading.test</name><grade>fail</grade></test><test><date>Sat Aug 06 16:29:41 KST 2011</date><name>level 0 reading.test</name><grade>fail</grade></test><test><date>Fri Aug 26 11:32:37 KST 2011</date><name>level 0 reading.test</name><grade>pass</grade></test><test><date>Tue Aug 30 11:59:48 KST 2011</date><name>level 1 reading.test</name><grade>pass</grade></test><test><date>Fri Oct 12 17:02:30 KST 2012</date><name>level 2 reading.test</name><grade>pass</grade></test></word><word><text>¿¬ÈÞ</text><definition>Long holiday</definition><date-of-entry>0</date-of-entry><reading-level>0</reading-level><writing-level>0</writing-level><id>3930872808523095697</id><test><date>Thu Dec 02 23:55:22 PST 2004</date><name>basic_writing.test</name><grade>pass</grade></test><test><date>Sat Jan 08 20:14:07 PST 2005</date><name>level 1 reading.test</name><grade>fail</grade></test><test><date>Sat Jan 29 19:05:26 PST 2005</date><name>level 2 writing.test</name><grade>pass</grade></test><test><date>Sun Jan 30 14:21:27 PST 2005</date><name>level 0 reading.test</name><grade>fail</grade></test><test><date>Sun Jan 30 14:23:45 PST 2005</date><name>level 0 reading.test</name><grade>pass</grade></test><test><date>Fri May 12 21:26:47 KST 2006</date><name>level 1 reading.test</name><grade>fail</grade></test><test><date>Wed Aug 02 16:07:43 KST 2006</date><name>level 0 reading.test</name><grade>fail</grade></test><test><date>Wed Aug 23 12:35:41 KST 2006</date><name>level 0 reading.test</name><grade>fail</grade></test><test><date>Fri Oct 26 21:18:28 KST 2007</date><name>level 3 writing.test</name><grade>fail</grade></test><test><date>Mon Dec 10 18:05:43 KST 2007</date><name>level 1 reading.test</name><grade>fail</grade></test><test><date>Sat Dec 29 12:09:42 KST 2007</date><name>level 2 writing.test</name><grade>fail</grade></test><test><date>Fri Apr 11 21:44:15 KST 2008</date><name>level 2 reading.test</name><grade>pass</grade></test><test><date>Fri Nov 07 09:17:35 KST 2008</date><name>level 3 writing.test</name><grade>fail</grade></test><test><date>Fri Dec 26 15:22:30 KST 2008</date><name>level 2 writing.test</name><grade>fail</grade></test><test><date>Fri Jul 03 16:35:11 KST 2009</date><name>level 1 writing.test</name><grade>fail</grade></test><test><date>Thu Aug 20 11:36:09 KST 2009</date><name>level 0 writing.test</name><grade>fail</grade></test><test><date>Tue Sep 01 16:58:54 KST 2009</date><name>level 3 reading.test</name><grade>pass</grade></test><test><date>Wed Sep 16 17:05:44 KST 2009</date><name>level 0 writing.test</name><grade>pass</grade></test><test><date>Tue Dec 15 15:07:23 KST 2009</date><name>level 1 writing.test</name><grade>fail</grade></test><test><date>Tue Jan 26 12:28:28 KST 2010</date><name>level 0 writing.test</name><grade>pass</grade></test><test><date>Sun May 02 14:23:14 KST 2010</date><name>level 1 writing.test</name><grade>fail</grade></test><test><date>Tue May 04 13:51:02 KST 2010</date><name>level 0 writing.test</name><grade>fail</grade></test><test><date>Mon May 17 16:20:26 KST 2010</date><name>level 0 writing.test</name><grade>pass</grade></test><test><date>Tue Jun 01 09:54:51 KST 2010</date><name>level 3 reading.test</name><grade>fail</grade></test><test><date>Tue Aug 03 11:49:51 KST 2010</date><name>level 1 writing.test</name><grade>fail</grade></test><test><date>Mon Oct 18 08:41:11 KST 2010</date><name>level 2 reading.test</name><grade>fail</grade></test><test><date>Mon Oct 18 15:55:55 KST 2010</date><name>level 1 writing.test</name><grade>pass</grade></test><test><date>Tue Nov 30 10:56:20 KST 2010</date><name>level 1 reading.test</name><grade>pass</grade></test><test><date>Wed Dec 01 11:17:12 KST 2010</date><name>level 2 writing.test</name><grade>pass</grade></test><test><date>Thu May 12 16:13:56 KST 2011</date><name>level 2 reading.test</name><grade>fail</grade></test><test><date>Mon Jul 25 13:02:47 KST 2011</date><name>level 1 reading.test</name><grade>fail</grade></test><test><date>Sat Aug 06 16:29:41 KST 2011</date><name>level 0 reading.test</name><grade>fail</grade></test><test><date>Fri Aug 26 11:32:37 KST 2011</date><name>level 0 reading.test</name><grade>pass</grade></test><test><date>Tue Aug 30 11:59:48 KST 2011</date><name>level 1 reading.test</name><grade>pass</grade></test><test><date>Fri Oct 12 17:02:30 KST 2012</date><name>level 2 reading.test</name><grade>pass</grade></test></word></words>
