<?xml version="1.0" encoding="euc-kr"?>
<vocab word_type="StringItem" word_constraint="ANY" word_maxSize="10" word_locale="kr" def_type="StringItem" def_constraint="ANY" def_maxSize="10" def_locale="en">
<word><text>찍다</text><definition>To stamp</definition><writing-level>3</writing-level><reading-level>3</reading-level><test><date>Fri Jan 28 08:17:40 PST 2005</date><file>level 0 writing.test</file><grade>pass</grade></test><test><date>Sun Jan 30 14:35:56 PST 2005</date><file>level 0 reading.test</file><grade>pass</grade></test><test><date>Wed Mar 23 11:24:51 PST 2005</date><file>level 1 writing.test</file><grade>pass</grade></test><test><date>Mon Nov 28 16:50:04 KST 2005</date><file>level 1 reading.test</file><grade>fail</grade></test><test><date>Sun Jan 08 16:05:46 KST 2006</date><file>level 0 reading.test</file><grade>pass</grade></test><test><date>Mon Jan 09 03:47:54 KST 2006</date><file>level 2 writing.test</file><grade>pass</grade></test><test><date>Tue Apr 18 19:16:06 KST 2006</date><file>level 1 reading.test</file><grade>pass</grade></test><test><date>Tue Apr 18 19:16:57 KST 2006</date><file>level 1 reading.test</file><grade>pass</grade></test><test><date>Thu Jun 29 19:06:48 KST 2006</date><file>level 2 reading.test</file><grade>pass</grade></test></word><word><text>가져오다</text><definition>To bring</definition><writing-level>3</writing-level><reading-level>3</reading-level><test><date>Fri Jan 28 08:17:40 PST 2005</date><file>level 0 writing.test</file><grade>pass</grade></test><test><date>Sun Jan 30 14:35:56 PST 2005</date><file>level 0 reading.test</file><grade>pass</grade></test><test><date>Wed Mar 23 11:24:51 PST 2005</date><file>level 1 writing.test</file><grade>fail</grade></test><test><date>Thu Oct 13 01:42:23 KST 2005</date><file>level 0 writing.test</file><grade>fail</grade></test><test><date>Fri Oct 14 01:57:02 KST 2005</date><file>level 0 writing.test</file><grade>pass</grade></test><test><date>Fri Nov 11 22:44:10 KST 2005</date><file>level 1 writing.test</file><grade>fail</grade></test><test><date>Mon Nov 21 16:46:08 KST 2005</date><file>level 0 writing.test</file><grade>fail</grade></test><test><date>Mon Nov 28 16:50:04 KST 2005</date><file>level 1 reading.test</file><grade>pass</grade></test><test><date>Wed Nov 30 12:43:26 KST 2005</date><file>level 0 writing.test</file><grade>pass</grade></test><test><date>Thu Dec 29 15:22:48 KST 2005</date><file>level 2 reading.test</file><grade>pass</grade></test><test><date>Thu Feb 23 19:18:47 KST 2006</date><file>level 3 reading.test</file><grade>pass</grade></test><test><date>Thu May 25 16:48:27 KST 2006</date><file>level 1 writing.test</file><grade>pass</grade></test><test><date>Mon Aug 28 19:36:12 KST 2006</date><file>level 2 writing.test</file><grade>pass</grade></test></word><word><text>두다</text><definition>To put down</definition><writing-level>1</writing-level><reading-level>3</reading-level><test><date>Fri Jan 28 08:17:40 PST 2005</date><file>level 0 writing.test</file><grade>fail</grade></test><test><date>Sat Jan 29 19:17:05 PST 2005</date><file>level 0 writing.test</file><grade>fail</grade></test><test><date>Sun Jan 30 14:35:56 PST 2005</date><file>level 0 reading.test</file><grade>fail</grade></test><test><date>Sun Jan 30 14:39:57 PST 2005</date><file>level 0 reading.test</file><grade>fail</grade></test><test><date>Sun Jan 30 14:44:36 PST 2005</date><file>level 0 reading.test</file><grade>fail</grade></test><test><date>Wed Feb 02 08:31:09 PST 2005</date><file>level 0 writing.test</file><grade>fail</grade></test><test><date>Wed Feb 02 21:09:01 PST 2005</date><file>level 0 writing.test</file><grade>fail</grade></test><test><date>Wed Feb 02 21:15:19 PST 2005</date><file>level 0 writing.test</file><grade>fail</grade></test><test><date>Sun Feb 13 19:17:04 PST 2005</date><file>level 0 writing.test</file><grade>fail</grade></test><test><date>Sun Feb 13 19:25:00 PST 2005</date><file>level 0 writing.test</file><grade>fail</grade></test><test><date>Sat Feb 19 21:51:48 PST 2005</date><file>level 0 writing.test</file><grade>fail</grade></test><test><date>Tue Feb 22 11:05:11 PST 2005</date><file>level 0 writing.test</file><grade>fail</grade></test><test><date>Fri Mar 04 09:54:13 PST 2005</date><file>level 0 writing.test</file><grade>fail</grade></test><test><date>Tue Mar 08 00:33:21 PST 2005</date><file>level 0 reading.test</file><grade>fail</grade></test><test><date>Wed Mar 23 10:55:43 PST 2005</date><file>level 0 reading.test</file><grade>fail</grade></test><test><date>Tue Oct 04 12:47:00 KST 2005</date><file>level 0 reading.test</file><grade>pass</grade></test><test><date>Thu Oct 13 01:42:23 KST 2005</date><file>level 0 writing.test</file><grade>fail</grade></test><test><date>Fri Oct 14 01:57:02 KST 2005</date><file>level 0 writing.test</file><grade>fail</grade></test><test><date>Fri Oct 14 02:00:07 KST 2005</date><file>level 0 writing.test</file><grade>fail</grade></test><test><date>Mon Oct 17 17:37:49 KST 2005</date><file>level 0 writing.test</file><grade>fail</grade></test><test><date>Thu Oct 27 12:04:28 KST 2005</date><file>level 0 writing.test</file><grade>fail</grade></test><test><date>Fri Oct 28 11:38:48 KST 2005</date><file>level 0 writing.test</file><grade>fail</grade></test><test><date>Mon Nov 21 16:46:08 KST 2005</date><file>level 0 writing.test</file><grade>fail</grade></test><test><date>Mon Nov 28 16:50:04 KST 2005</date><file>level 1 reading.test</file><grade>fail</grade></test><test><date>Wed Nov 30 12:43:26 KST 2005</date><file>level 0 writing.test</file><grade>fail</grade></test><test><date>Wed Nov 30 12:46:53 KST 2005</date><file>level 0 writing.test</file><grade>fail</grade></test><test><date>Tue Dec 27 11:50:09 KST 2005</date><file>level 0 writing.test</file><grade>fail</grade></test><test><date>Tue Dec 27 11:58:30 KST 2005</date><file>level 0 writing.test</file><grade>fail</grade></test><test><date>Tue Dec 27 22:39:38 KST 2005</date><file>level 0 writing.test</file><grade>fail</grade></test><test><date>Sun Jan 08 16:05:46 KST 2006</date><file>level 0 reading.test</file><grade>fail</grade></test><test><date>Sun Jan 08 16:09:26 KST 2006</date><file>level 0 writing.test</file><grade>pass</grade></test><test><date>Fri Jan 13 13:08:06 KST 2006</date><file>level 0 reading.test</file><grade>pass</grade></test><test><date>Tue Apr 18 19:12:40 KST 2006</date><file>level 1 reading.test</file><grade>fail</grade></test><test><date>Sun Apr 23 14:02:17 KST 2006</date><file>level 0 reading.test</file><grade>fail</grade></test><test><date>Sat May 13 09:18:59 KST 2006</date><file>level 0 reading.test</file><grade>pass</grade></test><test><date>Thu May 25 16:48:27 KST 2006</date><file>level 1 writing.test</file><grade>pass</grade></test><test><date>Mon Aug 28 19:36:12 KST 2006</date><file>level 2 writing.test</file><grade>fail</grade></test><test><date>Wed Oct 25 18:46:28 KST 2006</date><file>level 1 writing.test</file><grade>fail</grade></test><test><date>Tue Oct 31 19:07:31 KST 2006</date><file>level 0 writing.test</file><grade>fail</grade></test><test><date>Tue Oct 31 19:09:30 KST 2006</date><file>level 0 writing.test</file><grade>fail</grade></test><test><date>Sun Nov 12 15:34:29 KST 2006</date><file>level 1 reading.test</file><grade>pass</grade></test><test><date>Mon Nov 27 17:57:28 KST 2006</date><file>level 0 writing.test</file><grade>fail</grade></test><test><date>Fri Dec 15 19:48:27 KST 2006</date><file>level 0 writing.test</file><grade>pass</grade></test><test><date>Wed Jun 13 01:03:20 KST 2007</date><file>level 2 reading.test</file><grade>pass</grade></test></word><word><text>찾다</text><definition>To find</definition><writing-level>1</writing-level><reading-level>3</reading-level><test><date>Fri Jan 28 08:17:40 PST 2005</date><file>level 0 writing.test</file><grade>pass</grade></test><test><date>Sun Jan 30 14:35:56 PST 2005</date><file>level 0 reading.test</file><grade>fail</grade></test><test><date>Sun Jan 30 14:39:57 PST 2005</date><file>level 0 reading.test</file><grade>fail</grade></test><test><date>Sun Jan 30 14:44:36 PST 2005</date><file>level 0 reading.test</file><grade>fail</grade></test><test><date>Tue Mar 08 00:33:21 PST 2005</date><file>level 0 reading.test</file><grade>fail</grade></test><test><date>Wed Mar 23 10:55:43 PST 2005</date><file>level 0 reading.test</file><grade>pass</grade></test><test><date>Wed Mar 23 11:24:51 PST 2005</date><file>level 1 writing.test</file><grade>fail</grade></test><test><date>Thu Oct 13 01:42:23 KST 2005</date><file>level 0 writing.test</file><grade>fail</grade></test><test><date>Fri Oct 14 01:57:02 KST 2005</date><file>level 0 writing.test</file><grade>fail</grade></test><test><date>Fri Oct 14 02:00:07 KST 2005</date><file>level 0 writing.test</file><grade>fail</grade></test><test><date>Mon Oct 17 17:37:49 KST 2005</date><file>level 0 writing.test</file><grade>fail</grade></test><test><date>Thu Oct 27 12:04:28 KST 2005</date><file>level 0 writing.test</file><grade>pass</grade></test><test><date>Fri Nov 11 22:44:10 KST 2005</date><file>level 1 writing.test</file><grade>fail</grade></test><test><date>Mon Nov 21 16:46:08 KST 2005</date><file>level 0 writing.test</file><grade>pass</grade></test><test><date>Mon Nov 28 16:50:04 KST 2005</date><file>level 1 reading.test</file><grade>pass</grade></test><test><date>Thu Dec 29 15:22:48 KST 2005</date><file>level 2 reading.test</file><grade>pass</grade></test><test><date>Thu Feb 23 19:18:47 KST 2006</date><file>level 3 reading.test</file><grade>pass</grade></test><test><date>Thu May 25 16:48:27 KST 2006</date><file>level 1 writing.test</file><grade>fail</grade></test><test><date>Wed Aug 23 15:36:36 KST 2006</date><file>level 0 writing.test</file><grade>fail</grade></test><test><date>Wed Oct 18 19:52:42 KST 2006</date><file>level 0 writing.test</file><grade>pass</grade></test><test><date>Wed Oct 25 18:46:28 KST 2006</date><file>level 1 writing.test</file><grade>fail</grade></test><test><date>Tue Oct 31 19:07:31 KST 2006</date><file>level 0 writing.test</file><grade>pass</grade></test></word><word><text>다리다</text><definition>To iron</definition><writing-level>3</writing-level><reading-level>1</reading-level><test><date>Fri Jan 28 08:17:40 PST 2005</date><file>level 0 writing.test</file><grade>fail</grade></test><test><date>Sat Jan 29 19:17:05 PST 2005</date><file>level 0 writing.test</file><grade>fail</grade></test><test><date>Sun Jan 30 14:35:56 PST 2005</date><file>level 0 reading.test</file><grade>pass</grade></test><test><date>Wed Feb 02 08:31:09 PST 2005</date><file>level 0 writing.test</file><grade>fail</grade></test><test><date>Wed Feb 02 21:09:01 PST 2005</date><file>level 0 writing.test</file><grade>pass</grade></test><test><date>Wed Mar 23 11:24:51 PST 2005</date><file>level 1 writing.test</file><grade>fail</grade></test><test><date>Thu Oct 13 01:42:23 KST 2005</date><file>level 0 writing.test</file><grade>pass</grade></test><test><date>Fri Nov 11 22:44:10 KST 2005</date><file>level 1 writing.test</file><grade>fail</grade></test><test><date>Mon Nov 21 16:46:08 KST 2005</date><file>level 0 writing.test</file><grade>pass</grade></test><test><date>Mon Nov 28 16:50:04 KST 2005</date><file>level 1 reading.test</file><grade>pass</grade></test><test><date>Thu Dec 29 15:22:48 KST 2005</date><file>level 2 reading.test</file><grade>pass</grade></test><test><date>Thu Feb 23 19:18:47 KST 2006</date><file>level 3 reading.test</file><grade>fail</grade></test><test><date>Thu May 25 16:48:27 KST 2006</date><file>level 1 writing.test</file><grade>pass</grade></test><test><date>Thu Jun 29 19:06:48 KST 2006</date><file>level 2 reading.test</file><grade>fail</grade></test><test><date>Mon Aug 28 19:36:12 KST 2006</date><file>level 2 writing.test</file><grade>pass</grade></test><test><date>Sun Nov 12 15:34:29 KST 2006</date><file>level 1 reading.test</file><grade>fail</grade></test><test><date>Mon Jan 29 20:12:00 KST 2007</date><file>level 0 reading.test</file><grade>fail</grade></test><test><date>Fri Feb 09 20:15:00 KST 2007</date><file>level 0 reading.test</file><grade>fail</grade></test><test><date>Wed Feb 21 13:28:02 KST 2007</date><file>level 0 reading.test</file><grade>pass</grade></test><test><date>Sat Mar 31 16:34:40 KST 2007</date><file>level 1 reading.test</file><grade>fail</grade></test><test><date>Wed Jun 13 00:28:20 KST 2007</date><file>level 0 reading.test</file><grade>pass</grade></test></word><word><text>세탁소</text><definition>Dry cleaners</definition><writing-level>1</writing-level><reading-level>3</reading-level><test><date>Fri Jan 28 08:17:40 PST 2005</date><file>level 0 writing.test</file><grade>pass</grade></test><test><date>Sun Jan 30 14:35:56 PST 2005</date><file>level 0 reading.test</file><grade>pass</grade></test><test><date>Wed Mar 23 11:24:51 PST 2005</date><file>level 1 writing.test</file><grade>fail</grade></test><test><date>Thu Oct 13 01:42:23 KST 2005</date><file>level 0 writing.test</file><grade>fail</grade></test><test><date>Fri Oct 14 01:57:02 KST 2005</date><file>level 0 writing.test</file><grade>pass</grade></test><test><date>Fri Nov 11 22:44:10 KST 2005</date><file>level 1 writing.test</file><grade>fail</grade></test><test><date>Mon Nov 21 16:46:08 KST 2005</date><file>level 0 writing.test</file><grade>fail</grade></test><test><date>Mon Nov 28 16:50:04 KST 2005</date><file>level 1 reading.test</file><grade>pass</grade></test><test><date>Wed Nov 30 12:43:26 KST 2005</date><file>level 0 writing.test</file><grade>pass</grade></test><test><date>Thu Dec 29 15:22:48 KST 2005</date><file>level 2 reading.test</file><grade>fail</grade></test><test><date>Tue Apr 18 19:12:40 KST 2006</date><file>level 1 reading.test</file><grade>pass</grade></test><test><date>Thu May 25 16:48:27 KST 2006</date><file>level 1 writing.test</file><grade>fail</grade></test><test><date>Thu Jun 29 19:06:48 KST 2006</date><file>level 2 reading.test</file><grade>pass</grade></test><test><date>Wed Aug 23 15:36:36 KST 2006</date><file>level 0 writing.test</file><grade>pass</grade></test><test><date>Wed Oct 25 18:46:28 KST 2006</date><file>level 1 writing.test</file><grade>fail</grade></test><test><date>Tue Oct 31 19:07:31 KST 2006</date><file>level 0 writing.test</file><grade>pass</grade></test></word><word><text>촌스럽다</text><definition>unfashionable</definition><writing-level>3</writing-level><reading-level>3</reading-level><test><date>Sun Oct 16 16:30:51 KST 2005</date><file>level 0 reading.test</file><grade>fail</grade></test><test><date>Mon Oct 17 17:40:45 KST 2005</date><file>level 0 reading.test</file><grade>fail</grade></test><test><date>Mon Oct 17 23:48:25 KST 2005</date><file>level 0 reading.test</file><grade>fail</grade></test><test><date>Mon Oct 17 23:49:36 KST 2005</date><file>level 0 reading.test</file><grade>pass</grade></test><test><date>Fri Oct 28 11:38:48 KST 2005</date><file>level 0 writing.test</file><grade>fail</grade></test><test><date>Mon Nov 28 16:57:20 KST 2005</date><file>level 1 reading.test</file><grade>fail</grade></test><test><date>Fri Jan 13 13:10:23 KST 2006</date><file>level 0 reading.test</file><grade>pass</grade></test><test><date>Fri Jan 13 19:20:36 KST 2006</date><file>level 0 writing.test</file><grade>fail</grade></test><test><date>Sun Jan 15 14:06:52 KST 2006</date><file>level 0 writing.test</file><grade>fail</grade></test><test><date>Wed Feb 01 05:53:01 KST 2006</date><file>level 0 writing.test</file><grade>pass</grade></test><test><date>Tue Apr 18 19:12:40 KST 2006</date><file>level 1 reading.test</file><grade>fail</grade></test><test><date>Sun Apr 23 14:02:17 KST 2006</date><file>level 0 reading.test</file><grade>pass</grade></test><test><date>Mon Apr 24 19:21:16 KST 2006</date><file>level 1 reading.test</file><grade>pass</grade></test><test><date>Thu May 25 16:48:27 KST 2006</date><file>level 1 writing.test</file><grade>pass</grade></test><test><date>Thu Jun 29 19:06:48 KST 2006</date><file>level 2 reading.test</file><grade>pass</grade></test><test><date>Mon Aug 28 19:36:12 KST 2006</date><file>level 2 writing.test</file><grade>pass</grade></test></word><word><text>유사한</text><definition>similar</definition><writing-level>1</writing-level><reading-level>3</reading-level><test><date>Fri Jan 28 08:17:40 PST 2005</date><file>level 0 writing.test</file><grade>fail</grade></test><test><date>Sat Jan 29 19:17:05 PST 2005</date><file>level 0 writing.test</file><grade>fail</grade></test><test><date>Sun Jan 30 14:35:56 PST 2005</date><file>level 0 reading.test</file><grade>pass</grade></test><test><date>Wed Feb 02 08:31:09 PST 2005</date><file>level 0 writing.test</file><grade>fail</grade></test><test><date>Wed Feb 02 21:09:01 PST 2005</date><file>level 0 writing.test</file><grade>fail</grade></test><test><date>Wed Feb 02 21:15:19 PST 2005</date><file>level 0 writing.test</file><grade>fail</grade></test><test><date>Sun Feb 13 19:17:04 PST 2005</date><file>level 0 writing.test</file><grade>fail</grade></test><test><date>Sun Feb 13 19:25:00 PST 2005</date><file>level 0 writing.test</file><grade>fail</grade></test><test><date>Sat Feb 19 21:51:48 PST 2005</date><file>level 0 writing.test</file><grade>fail</grade></test><test><date>Tue Feb 22 11:05:11 PST 2005</date><file>level 0 writing.test</file><grade>fail</grade></test><test><date>Fri Mar 04 09:54:13 PST 2005</date><file>level 0 writing.test</file><grade>fail</grade></test><test><date>Thu Oct 13 01:42:23 KST 2005</date><file>level 0 writing.test</file><grade>fail</grade></test><test><date>Fri Oct 14 01:57:02 KST 2005</date><file>level 0 writing.test</file><grade>fail</grade></test><test><date>Fri Oct 14 02:00:07 KST 2005</date><file>level 0 writing.test</file><grade>fail</grade></test><test><date>Mon Oct 17 17:37:49 KST 2005</date><file>level 0 writing.test</file><grade>pass</grade></test><test><date>Fri Nov 11 22:44:10 KST 2005</date><file>level 1 writing.test</file><grade>pass</grade></test><test><date>Mon Nov 28 16:50:04 KST 2005</date><file>level 1 reading.test</file><grade>pass</grade></test><test><date>Thu Dec 29 15:26:13 KST 2005</date><file>level 2 reading.test</file><grade>pass</grade></test><test><date>Mon Jan 09 03:47:54 KST 2006</date><file>level 2 writing.test</file><grade>fail</grade></test><test><date>Mon May 29 03:11:47 KST 2006</date><file>level 1 writing.test</file><grade>pass</grade></test><test><date>Mon Aug 28 19:36:12 KST 2006</date><file>level 2 writing.test</file><grade>fail</grade></test><test><date>Wed Oct 25 18:48:39 KST 2006</date><file>level 1 writing.test</file><grade>fail</grade></test><test><date>Tue Oct 31 19:07:31 KST 2006</date><file>level 0 writing.test</file><grade>pass</grade></test></word><word><text>고급창녀</text><definition>courtesan</definition><writing-level>2</writing-level><reading-level>3</reading-level><test><date>Fri Jan 28 08:17:40 PST 2005</date><file>level 0 writing.test</file><grade>pass</grade></test><test><date>Sun Jan 30 14:35:56 PST 2005</date><file>level 0 reading.test</file><grade>fail</grade></test><test><date>Sun Jan 30 14:39:57 PST 2005</date><file>level 0 reading.test</file><grade>fail</grade></test><test><date>Sun Jan 30 14:44:36 PST 2005</date><file>level 0 reading.test</file><grade>pass</grade></test><test><date>Wed Mar 23 11:24:51 PST 2005</date><file>level 1 writing.test</file><grade>fail</grade></test><test><date>Thu Oct 13 01:42:23 KST 2005</date><file>level 0 writing.test</file><grade>pass</grade></test><test><date>Fri Nov 11 22:44:10 KST 2005</date><file>level 1 writing.test</file><grade>fail</grade></test><test><date>Mon Nov 21 16:46:08 KST 2005</date><file>level 0 writing.test</file><grade>fail</grade></test><test><date>Mon Nov 28 16:50:04 KST 2005</date><file>level 1 reading.test</file><grade>fail</grade></test><test><date>Wed Nov 30 12:43:26 KST 2005</date><file>level 0 writing.test</file><grade>fail</grade></test><test><date>Wed Nov 30 12:46:53 KST 2005</date><file>level 0 writing.test</file><grade>fail</grade></test><test><date>Tue Dec 27 11:50:09 KST 2005</date><file>level 0 writing.test</file><grade>fail</grade></test><test><date>Tue Dec 27 11:58:30 KST 2005</date><file>level 0 writing.test</file><grade>pass</grade></test><test><date>Fri Jan 13 13:08:06 KST 2006</date><file>level 0 reading.test</file><grade>pass</grade></test><test><date>Tue Apr 18 19:12:40 KST 2006</date><file>level 1 reading.test</file><grade>pass</grade></test><test><date>Thu May 25 16:48:27 KST 2006</date><file>level 1 writing.test</file><grade>fail</grade></test><test><date>Thu Jun 29 19:06:48 KST 2006</date><file>level 2 reading.test</file><grade>pass</grade></test><test><date>Wed Aug 23 15:36:36 KST 2006</date><file>level 0 writing.test</file><grade>fail</grade></test><test><date>Wed Oct 18 19:52:42 KST 2006</date><file>level 0 writing.test</file><grade>pass</grade></test><test><date>Wed Oct 25 18:46:28 KST 2006</date><file>level 1 writing.test</file><grade>pass</grade></test></word><word><text>조용하게</text><definition>quietly</definition><writing-level>1</writing-level><reading-level>3</reading-level><test><date>Fri Jan 28 08:17:40 PST 2005</date><file>level 0 writing.test</file><grade>fail</grade></test><test><date>Sat Jan 29 19:17:05 PST 2005</date><file>level 0 writing.test</file><grade>pass</grade></test><test><date>Sun Jan 30 14:35:56 PST 2005</date><file>level 0 reading.test</file><grade>pass</grade></test><test><date>Fri Nov 11 22:44:10 KST 2005</date><file>level 1 writing.test</file><grade>fail</grade></test><test><date>Mon Nov 21 16:46:08 KST 2005</date><file>level 0 writing.test</file><grade>pass</grade></test><test><date>Mon Nov 28 16:50:04 KST 2005</date><file>level 1 reading.test</file><grade>pass</grade></test><test><date>Thu Dec 29 15:22:48 KST 2005</date><file>level 2 reading.test</file><grade>pass</grade></test><test><date>Thu Feb 23 19:18:47 KST 2006</date><file>level 3 reading.test</file><grade>fail</grade></test><test><date>Thu May 25 16:48:27 KST 2006</date><file>level 1 writing.test</file><grade>pass</grade></test><test><date>Thu Jun 29 19:08:14 KST 2006</date><file>level 2 reading.test</file><grade>pass</grade></test><test><date>Mon Aug 28 19:36:12 KST 2006</date><file>level 2 writing.test</file><grade>fail</grade></test><test><date>Wed Oct 25 18:46:28 KST 2006</date><file>level 1 writing.test</file><grade>fail</grade></test><test><date>Tue Oct 31 19:07:31 KST 2006</date><file>level 0 writing.test</file><grade>pass</grade></test></word><word><text>체하다</text><definition>To have indigestion</definition><writing-level>2</writing-level><reading-level>1</reading-level><test><date>Fri Jan 28 08:17:40 PST 2005</date><file>level 0 writing.test</file><grade>pass</grade></test><test><date>Sun Jan 30 14:35:56 PST 2005</date><file>level 0 reading.test</file><grade>fail</grade></test><test><date>Sun Jan 30 14:39:57 PST 2005</date><file>level 0 reading.test</file><grade>fail</grade></test><test><date>Sun Jan 30 14:44:36 PST 2005</date><file>level 0 reading.test</file><grade>fail</grade></test><test><date>Tue Mar 08 00:33:21 PST 2005</date><file>level 0 reading.test</file><grade>fail</grade></test><test><date>Wed Mar 23 10:55:43 PST 2005</date><file>level 0 reading.test</file><grade>fail</grade></test><test><date>Wed Mar 23 11:24:51 PST 2005</date><file>level 1 writing.test</file><grade>fail</grade></test><test><date>Tue Oct 04 12:47:00 KST 2005</date><file>level 0 reading.test</file><grade>fail</grade></test><test><date>Tue Oct 04 18:00:09 KST 2005</date><file>level 0 reading.test</file><grade>fail</grade></test><test><date>Thu Oct 13 01:42:23 KST 2005</date><file>level 0 writing.test</file><grade>fail</grade></test><test><date>Fri Oct 14 01:57:02 KST 2005</date><file>level 0 writing.test</file><grade>fail</grade></test><test><date>Fri Oct 14 02:00:07 KST 2005</date><file>level 0 writing.test</file><grade>fail</grade></test><test><date>Sun Oct 16 16:22:21 KST 2005</date><file>level 0 reading.test</file><grade>fail</grade></test><test><date>Sun Oct 16 16:24:23 KST 2005</date><file>level 0 reading.test</file><grade>pass</grade></test><test><date>Mon Oct 17 17:37:49 KST 2005</date><file>level 0 writing.test</file><grade>pass</grade></test><test><date>Fri Nov 11 22:38:24 KST 2005</date><file>level 1 writing.test</file><grade>fail</grade></test><test><date>Mon Nov 21 16:46:08 KST 2005</date><file>level 0 writing.test</file><grade>fail</grade></test><test><date>Mon Nov 28 16:50:04 KST 2005</date><file>level 1 reading.test</file><grade>pass</grade></test><test><date>Wed Nov 30 12:43:26 KST 2005</date><file>level 0 writing.test</file><grade>fail</grade></test><test><date>Wed Nov 30 12:46:53 KST 2005</date><file>level 0 writing.test</file><grade>fail</grade></test><test><date>Tue Dec 27 11:50:09 KST 2005</date><file>level 0 writing.test</file><grade>fail</grade></test><test><date>Tue Dec 27 11:58:30 KST 2005</date><file>level 0 writing.test</file><grade>fail</grade></test><test><date>Tue Dec 27 22:39:38 KST 2005</date><file>level 0 writing.test</file><grade>fail</grade></test><test><date>Thu Dec 29 15:22:48 KST 2005</date><file>level 2 reading.test</file><grade>pass</grade></test><test><date>Sun Jan 08 16:09:26 KST 2006</date><file>level 0 writing.test</file><grade>pass</grade></test><test><date>Thu Feb 23 19:18:47 KST 2006</date><file>level 3 reading.test</file><grade>fail</grade></test><test><date>Thu May 25 16:48:27 KST 2006</date><file>level 1 writing.test</file><grade>fail</grade></test><test><date>Thu Jun 29 19:06:48 KST 2006</date><file>level 2 reading.test</file><grade>fail</grade></test><test><date>Wed Aug 23 15:36:36 KST 2006</date><file>level 0 writing.test</file><grade>fail</grade></test><test><date>Wed Oct 18 19:52:42 KST 2006</date><file>level 0 writing.test</file><grade>pass</grade></test><test><date>Wed Oct 25 18:46:28 KST 2006</date><file>level 1 writing.test</file><grade>pass</grade></test><test><date>Sun Nov 12 15:34:29 KST 2006</date><file>level 1 reading.test</file><grade>pass</grade></test><test><date>Wed Jun 13 01:03:20 KST 2007</date><file>level 2 reading.test</file><grade>fail</grade></test></word><word><text>계약</text><definition>contract</definition><writing-level>1</writing-level><reading-level>1</reading-level><test><date>Sat Jan 29 19:17:05 PST 2005</date><file>level 0 writing.test</file><grade>fail</grade></test><test><date>Sun Jan 30 14:39:57 PST 2005</date><file>level 0 reading.test</file><grade>pass</grade></test><test><date>Wed Feb 02 08:31:09 PST 2005</date><file>level 0 writing.test</file><grade>fail</grade></test><test><date>Wed Feb 02 21:09:01 PST 2005</date><file>level 0 writing.test</file><grade>pass</grade></test><test><date>Wed Mar 23 11:24:51 PST 2005</date><file>level 1 writing.test</file><grade>fail</grade></test><test><date>Thu Oct 13 01:42:23 KST 2005</date><file>level 0 writing.test</file><grade>pass</grade></test><test><date>Fri Nov 11 22:38:24 KST 2005</date><file>level 1 writing.test</file><grade>fail</grade></test><test><date>Mon Nov 21 16:46:08 KST 2005</date><file>level 0 writing.test</file><grade>fail</grade></test><test><date>Mon Nov 28 16:51:14 KST 2005</date><file>level 1 reading.test</file><grade>fail</grade></test><test><date>Wed Nov 30 12:43:26 KST 2005</date><file>level 0 writing.test</file><grade>fail</grade></test><test><date>Wed Nov 30 12:46:53 KST 2005</date><file>level 0 writing.test</file><grade>fail</grade></test><test><date>Tue Dec 27 11:50:09 KST 2005</date><file>level 0 writing.test</file><grade>pass</grade></test><test><date>Fri Jan 13 13:08:06 KST 2006</date><file>level 0 reading.test</file><grade>pass</grade></test><test><date>Tue Apr 18 19:12:40 KST 2006</date><file>level 1 reading.test</file><grade>fail</grade></test><test><date>Sun Apr 23 14:02:17 KST 2006</date><file>level 0 reading.test</file><grade>fail</grade></test><test><date>Sat May 13 09:18:59 KST 2006</date><file>level 0 reading.test</file><grade>pass</grade></test><test><date>Thu May 25 16:48:27 KST 2006</date><file>level 1 writing.test</file><grade>fail</grade></test><test><date>Wed Aug 23 15:36:36 KST 2006</date><file>level 0 writing.test</file><grade>fail</grade></test><test><date>Wed Oct 18 19:52:42 KST 2006</date><file>level 0 writing.test</file><grade>pass</grade></test><test><date>Wed Oct 25 18:46:28 KST 2006</date><file>level 1 writing.test</file><grade>fail</grade></test><test><date>Tue Oct 31 19:07:31 KST 2006</date><file>level 0 writing.test</file><grade>fail</grade></test><test><date>Tue Oct 31 19:09:30 KST 2006</date><file>level 0 writing.test</file><grade>fail</grade></test><test><date>Sun Nov 12 15:34:29 KST 2006</date><file>level 1 reading.test</file><grade>pass</grade></test><test><date>Mon Nov 27 17:57:28 KST 2006</date><file>level 0 writing.test</file><grade>fail</grade></test><test><date>Fri Dec 15 19:48:27 KST 2006</date><file>level 0 writing.test</file><grade>pass</grade></test><test><date>Wed Jun 13 01:03:20 KST 2007</date><file>level 2 reading.test</file><grade>fail</grade></test></word><word><text>은</text><definition>silver</definition><writing-level>3</writing-level><reading-level>3</reading-level><test><date>Sat Jan 29 19:17:05 PST 2005</date><file>level 0 writing.test</file><grade>pass</grade></test><test><date>Sun Jan 30 14:39:57 PST 2005</date><file>level 0 reading.test</file><grade>pass</grade></test><test><date>Wed Mar 23 11:24:51 PST 2005</date><file>level 1 writing.test</file><grade>pass</grade></test><test><date>Mon Nov 28 16:51:14 KST 2005</date><file>level 1 reading.test</file><grade>pass</grade></test><test><date>Thu Dec 29 15:22:48 KST 2005</date><file>level 2 reading.test</file><grade>pass</grade></test><test><date>Mon Jan 09 03:47:54 KST 2006</date><file>level 2 writing.test</file><grade>pass</grade></test><test><date>Thu Feb 23 19:18:47 KST 2006</date><file>level 3 reading.test</file><grade>pass</grade></test></word><word><text>놀란</text><definition>surprise</definition><writing-level>3</writing-level><reading-level>1</reading-level><test><date>Sat Jan 29 19:17:05 PST 2005</date><file>level 0 writing.test</file><grade>fail</grade></test><test><date>Sun Jan 30 14:39:57 PST 2005</date><file>level 0 reading.test</file><grade>fail</grade></test><test><date>Sun Jan 30 14:44:36 PST 2005</date><file>level 0 reading.test</file><grade>fail</grade></test><test><date>Wed Feb 02 08:31:09 PST 2005</date><file>level 0 writing.test</file><grade>fail</grade></test><test><date>Wed Feb 02 21:09:01 PST 2005</date><file>level 0 writing.test</file><grade>pass</grade></test><test><date>Tue Mar 08 00:33:21 PST 2005</date><file>level 0 reading.test</file><grade>fail</grade></test><test><date>Wed Mar 23 10:55:43 PST 2005</date><file>level 0 reading.test</file><grade>fail</grade></test><test><date>Wed Mar 23 11:24:51 PST 2005</date><file>level 1 writing.test</file><grade>fail</grade></test><test><date>Tue Oct 04 12:47:00 KST 2005</date><file>level 0 reading.test</file><grade>fail</grade></test><test><date>Tue Oct 04 18:00:09 KST 2005</date><file>level 0 reading.test</file><grade>fail</grade></test><test><date>Thu Oct 13 01:42:23 KST 2005</date><file>level 0 writing.test</file><grade>fail</grade></test><test><date>Fri Oct 14 01:57:02 KST 2005</date><file>level 0 writing.test</file><grade>pass</grade></test><test><date>Sun Oct 16 16:22:21 KST 2005</date><file>level 0 reading.test</file><grade>fail</grade></test><test><date>Sun Oct 16 16:24:23 KST 2005</date><file>level 0 reading.test</file><grade>pass</grade></test><test><date>Fri Nov 11 22:38:24 KST 2005</date><file>level 1 writing.test</file><grade>fail</grade></test><test><date>Mon Nov 21 16:46:08 KST 2005</date><file>level 0 writing.test</file><grade>fail</grade></test><test><date>Mon Nov 28 16:51:14 KST 2005</date><file>level 1 reading.test</file><grade>fail</grade></test><test><date>Wed Nov 30 12:43:26 KST 2005</date><file>level 0 writing.test</file><grade>pass</grade></test><test><date>Fri Jan 13 13:08:06 KST 2006</date><file>level 0 reading.test</file><grade>pass</grade></test><test><date>Tue Apr 18 19:12:40 KST 2006</date><file>level 1 reading.test</file><grade>fail</grade></test><test><date>Sun Apr 23 14:02:17 KST 2006</date><file>level 0 reading.test</file><grade>fail</grade></test><test><date>Sat May 13 09:18:59 KST 2006</date><file>level 0 reading.test</file><grade>fail</grade></test><test><date>Mon May 29 03:11:47 KST 2006</date><file>level 1 writing.test</file><grade>pass</grade></test><test><date>Tue Jun 06 21:25:09 KST 2006</date><file>level 0 reading.test</file><grade>fail</grade></test><test><date>Thu Jun 15 19:37:53 KST 2006</date><file>level 0 reading.test</file><grade>pass</grade></test><test><date>Mon Aug 28 19:36:12 KST 2006</date><file>level 2 writing.test</file><grade>pass</grade></test><test><date>Sun Nov 12 15:34:29 KST 2006</date><file>level 1 reading.test</file><grade>fail</grade></test><test><date>Mon Jan 29 20:12:00 KST 2007</date><file>level 0 reading.test</file><grade>pass</grade></test><test><date>Sat Mar 31 16:34:40 KST 2007</date><file>level 1 reading.test</file><grade>fail</grade></test><test><date>Wed Jun 13 00:28:20 KST 2007</date><file>level 0 reading.test</file><grade>pass</grade></test></word><word><text>무식한</text><definition>ignorant</definition><writing-level>3</writing-level><reading-level>3</reading-level><test><date>Sat Jan 29 19:17:05 PST 2005</date><file>level 0 writing.test</file><grade>fail</grade></test><test><date>Sun Jan 30 14:39:57 PST 2005</date><file>level 0 reading.test</file><grade>fail</grade></test><test><date>Sun Jan 30 14:44:36 PST 2005</date><file>level 0 reading.test</file><grade>fail</grade></test><test><date>Wed Feb 02 08:31:09 PST 2005</date><file>level 0 writing.test</file><grade>fail</grade></test><test><date>Wed Feb 02 21:09:01 PST 2005</date><file>level 0 writing.test</file><grade>fail</grade></test><test><date>Wed Feb 02 21:15:19 PST 2005</date><file>level 0 writing.test</file><grade>fail</grade></test><test><date>Sun Feb 13 19:17:04 PST 2005</date><file>level 0 writing.test</file><grade>fail</grade></test><test><date>Sun Feb 13 19:25:00 PST 2005</date><file>level 0 writing.test</file><grade>pass</grade></test><test><date>Tue Mar 08 00:33:21 PST 2005</date><file>level 0 reading.test</file><grade>fail</grade></test><test><date>Wed Mar 23 10:55:43 PST 2005</date><file>level 0 reading.test</file><grade>fail</grade></test><test><date>Tue Oct 04 12:47:00 KST 2005</date><file>level 0 reading.test</file><grade>fail</grade></test><test><date>Tue Oct 04 18:00:09 KST 2005</date><file>level 0 reading.test</file><grade>fail</grade></test><test><date>Sun Oct 16 16:22:21 KST 2005</date><file>level 0 reading.test</file><grade>pass</grade></test><test><date>Fri Nov 11 22:38:24 KST 2005</date><file>level 1 writing.test</file><grade>pass</grade></test><test><date>Mon Nov 28 16:51:14 KST 2005</date><file>level 1 reading.test</file><grade>pass</grade></test><test><date>Thu Dec 29 15:22:48 KST 2005</date><file>level 2 reading.test</file><grade>fail</grade></test><test><date>Mon Jan 09 03:47:54 KST 2006</date><file>level 2 writing.test</file><grade>pass</grade></test><test><date>Tue Apr 18 19:12:40 KST 2006</date><file>level 1 reading.test</file><grade>fail</grade></test><test><date>Sun Apr 23 14:02:17 KST 2006</date><file>level 0 reading.test</file><grade>fail</grade></test><test><date>Sat May 13 09:18:59 KST 2006</date><file>level 0 reading.test</file><grade>pass</grade></test><test><date>Sun Nov 12 15:34:29 KST 2006</date><file>level 1 reading.test</file><grade>pass</grade></test><test><date>Wed Jun 13 01:03:20 KST 2007</date><file>level 2 reading.test</file><grade>pass</grade></test></word><word><text>모험</text><definition>adventure</definition><writing-level>3</writing-level><reading-level>3</reading-level><test><date>Sat Jan 29 19:17:05 PST 2005</date><file>level 0 writing.test</file><grade>pass</grade></test><test><date>Sun Jan 30 14:39:57 PST 2005</date><file>level 0 reading.test</file><grade>pass</grade></test><test><date>Fri Nov 11 22:38:24 KST 2005</date><file>level 1 writing.test</file><grade>pass</grade></test><test><date>Mon Nov 28 16:51:14 KST 2005</date><file>level 1 reading.test</file><grade>pass</grade></test><test><date>Thu Dec 29 15:22:48 KST 2005</date><file>level 2 reading.test</file><grade>pass</grade></test><test><date>Mon Jan 09 03:52:01 KST 2006</date><file>level 2 writing.test</file><grade>pass</grade></test><test><date>Thu Feb 23 19:18:47 KST 2006</date><file>level 3 reading.test</file><grade>pass</grade></test></word><word><text>지하실</text><definition>basement</definition><writing-level>2</writing-level><reading-level>3</reading-level><test><date>Sat Jan 29 19:17:05 PST 2005</date><file>level 0 writing.test</file><grade>pass</grade></test><test><date>Sun Jan 30 14:39:57 PST 2005</date><file>level 0 reading.test</file><grade>pass</grade></test><test><date>Fri Nov 11 22:38:24 KST 2005</date><file>level 1 writing.test</file><grade>fail</grade></test><test><date>Mon Nov 28 16:51:14 KST 2005</date><file>level 1 reading.test</file><grade>pass</grade></test><test><date>Wed Nov 30 12:43:26 KST 2005</date><file>level 0 writing.test</file><grade>fail</grade></test><test><date>Wed Nov 30 12:46:53 KST 2005</date><file>level 0 writing.test</file><grade>fail</grade></test><test><date>Tue Dec 27 11:50:09 KST 2005</date><file>level 0 writing.test</file><grade>fail</grade></test><test><date>Tue Dec 27 11:58:30 KST 2005</date><file>level 0 writing.test</file><grade>pass</grade></test><test><date>Thu Dec 29 15:22:48 KST 2005</date><file>level 2 reading.test</file><grade>pass</grade></test><test><date>Thu Feb 23 19:18:47 KST 2006</date><file>level 3 reading.test</file><grade>pass</grade></test><test><date>Mon May 29 03:11:47 KST 2006</date><file>level 1 writing.test</file><grade>fail</grade></test><test><date>Wed Aug 23 15:36:36 KST 2006</date><file>level 0 writing.test</file><grade>fail</grade></test><test><date>Wed Oct 18 19:52:42 KST 2006</date><file>level 0 writing.test</file><grade>pass</grade></test><test><date>Wed Oct 25 18:46:28 KST 2006</date><file>level 1 writing.test</file><grade>pass</grade></test></word><word><text>다락</text><definition>attic</definition><writing-level>1</writing-level><reading-level>3</reading-level><test><date>Sun Jan 30 14:44:36 PST 2005</date><file>level 0 reading.test</file><grade>fail</grade></test><test><date>Wed Feb 02 08:31:09 PST 2005</date><file>level 0 writing.test</file><grade>pass</grade></test><test><date>Tue Mar 08 00:33:21 PST 2005</date><file>level 0 reading.test</file><grade>pass</grade></test><test><date>Fri Nov 11 22:38:24 KST 2005</date><file>level 1 writing.test</file><grade>fail</grade></test><test><date>Mon Nov 28 16:51:14 KST 2005</date><file>level 1 reading.test</file><grade>pass</grade></test><test><date>Wed Nov 30 12:43:26 KST 2005</date><file>level 0 writing.test</file><grade>pass</grade></test><test><date>Thu Dec 29 15:23:56 KST 2005</date><file>level 2 reading.test</file><grade>pass</grade></test><test><date>Thu Feb 23 19:18:47 KST 2006</date><file>level 3 reading.test</file><grade>pass</grade></test><test><date>Mon May 29 03:11:47 KST 2006</date><file>level 1 writing.test</file><grade>fail</grade></test><test><date>Wed Aug 23 15:36:36 KST 2006</date><file>level 0 writing.test</file><grade>fail</grade></test><test><date>Wed Oct 18 19:52:42 KST 2006</date><file>level 0 writing.test</file><grade>pass</grade></test><test><date>Wed Oct 25 18:46:28 KST 2006</date><file>level 1 writing.test</file><grade>fail</grade></test><test><date>Tue Oct 31 19:07:31 KST 2006</date><file>level 0 writing.test</file><grade>pass</grade></test></word><word><text>옥상</text><definition>rooftop</definition><writing-level>3</writing-level><reading-level>3</reading-level><test><date>Sun Jan 30 14:44:36 PST 2005</date><file>level 0 reading.test</file><grade>fail</grade></test><test><date>Wed Feb 02 08:31:09 PST 2005</date><file>level 0 writing.test</file><grade>fail</grade></test><test><date>Wed Feb 02 21:09:01 PST 2005</date><file>level 0 writing.test</file><grade>pass</grade></test><test><date>Tue Mar 08 00:33:21 PST 2005</date><file>level 0 reading.test</file><grade>pass</grade></test><test><date>Fri Nov 11 22:38:24 KST 2005</date><file>level 1 writing.test</file><grade>pass</grade></test><test><date>Mon Nov 28 16:51:14 KST 2005</date><file>level 1 reading.test</file><grade>fail</grade></test><test><date>Mon Jan 09 03:52:01 KST 2006</date><file>level 2 writing.test</file><grade>pass</grade></test><test><date>Fri Jan 13 13:08:06 KST 2006</date><file>level 0 reading.test</file><grade>fail</grade></test><test><date>Tue Apr 18 19:12:40 KST 2006</date><file>level 1 reading.test</file><grade>fail</grade></test><test><date>Sat May 13 09:18:59 KST 2006</date><file>level 0 reading.test</file><grade>pass</grade></test><test><date>Sun Nov 12 15:34:29 KST 2006</date><file>level 1 reading.test</file><grade>pass</grade></test><test><date>Wed Jun 13 01:03:20 KST 2007</date><file>level 2 reading.test</file><grade>pass</grade></test></word><word><text>차고</text><definition>garage</definition><writing-level>1</writing-level><reading-level>3</reading-level><test><date>Sun Jan 30 14:44:36 PST 2005</date><file>level 0 reading.test</file><grade>fail</grade></test><test><date>Wed Feb 02 08:31:09 PST 2005</date><file>level 0 writing.test</file><grade>pass</grade></test><test><date>Tue Mar 08 00:33:21 PST 2005</date><file>level 0 reading.test</file><grade>fail</grade></test><test><date>Wed Mar 23 10:55:43 PST 2005</date><file>level 0 reading.test</file><grade>pass</grade></test><test><date>Fri Nov 11 22:38:24 KST 2005</date><file>level 1 writing.test</file><grade>fail</grade></test><test><date>Mon Nov 28 16:51:14 KST 2005</date><file>level 1 reading.test</file><grade>pass</grade></test><test><date>Wed Nov 30 12:43:26 KST 2005</date><file>level 0 writing.test</file><grade>pass</grade></test><test><date>Thu Dec 29 15:23:56 KST 2005</date><file>level 2 reading.test</file><grade>pass</grade></test><test><date>Thu Feb 23 19:18:47 KST 2006</date><file>level 3 reading.test</file><grade>pass</grade></test><test><date>Mon May 29 03:11:47 KST 2006</date><file>level 1 writing.test</file><grade>pass</grade></test><test><date>Mon Aug 28 19:36:12 KST 2006</date><file>level 2 writing.test</file><grade>fail</grade></test><test><date>Wed Oct 25 18:46:28 KST 2006</date><file>level 1 writing.test</file><grade>fail</grade></test><test><date>Tue Oct 31 19:07:31 KST 2006</date><file>level 0 writing.test</file><grade>fail</grade></test><test><date>Tue Oct 31 19:09:30 KST 2006</date><file>level 0 writing.test</file><grade>fail</grade></test><test><date>Mon Nov 27 17:57:28 KST 2006</date><file>level 0 writing.test</file><grade>pass</grade></test></word><word><text>경치</text><definition>view</definition><writing-level>3</writing-level><reading-level>3</reading-level><test><date>Fri Jan 28 08:19:00 PST 2005</date><file>level 0 writing.test</file><grade>fail</grade></test><test><date>Sun Jan 30 14:38:22 PST 2005</date><file>level 0 reading.test</file><grade>fail</grade></test><test><date>Sun Jan 30 14:44:36 PST 2005</date><file>level 0 reading.test</file><grade>fail</grade></test><test><date>Wed Feb 02 08:31:09 PST 2005</date><file>level 0 writing.test</file><grade>fail</grade></test><test><date>Wed Feb 02 21:09:01 PST 2005</date><file>level 0 writing.test</file><grade>pass</grade></test><test><date>Tue Mar 08 00:33:21 PST 2005</date><file>level 0 reading.test</file><grade>fail</grade></test><test><date>Wed Mar 23 10:55:43 PST 2005</date><file>level 0 reading.test</file><grade>fail</grade></test><test><date>Tue Oct 04 12:47:00 KST 2005</date><file>level 0 reading.test</file><grade>pass</grade></test><test><date>Fri Nov 11 22:38:24 KST 2005</date><file>level 1 writing.test</file><grade>fail</grade></test><test><date>Mon Nov 28 16:51:14 KST 2005</date><file>level 1 reading.test</file><grade>pass</grade></test><test><date>Wed Nov 30 12:46:53 KST 2005</date><file>level 0 writing.test</file><grade>pass</grade></test><test><date>Thu Dec 29 15:23:56 KST 2005</date><file>level 2 reading.test</file><grade>pass</grade></test><test><date>Mon May 29 03:11:47 KST 2006</date><file>level 1 writing.test</file><grade>pass</grade></test><test><date>Mon Aug 28 19:36:12 KST 2006</date><file>level 2 writing.test</file><grade>pass</grade></test></word><word><text>한턱내</text><definition>You buy</definition><writing-level>1</writing-level><reading-level>3</reading-level><test><date>Wed Feb 02 21:09:01 PST 2005</date><file>level 0 writing.test</file><grade>fail</grade></test><test><date>Wed Feb 02 21:15:19 PST 2005</date><file>level 0 writing.test</file><grade>fail</grade></test><test><date>Sun Feb 13 19:17:04 PST 2005</date><file>level 0 writing.test</file><grade>fail</grade></test><test><date>Sun Feb 13 19:25:00 PST 2005</date><file>level 0 writing.test</file><grade>fail</grade></test><test><date>Sat Feb 19 21:51:48 PST 2005</date><file>level 0 writing.test</file><grade>fail</grade></test><test><date>Tue Feb 22 11:05:11 PST 2005</date><file>level 0 writing.test</file><grade>fail</grade></test><test><date>Thu Mar 03 11:19:40 PST 2005</date><file>level 0 writing.test</file><grade>fail</grade></test><test><date>Fri Mar 04 09:54:13 PST 2005</date><file>level 0 writing.test</file><grade>fail</grade></test><test><date>Tue Mar 08 00:33:21 PST 2005</date><file>level 0 reading.test</file><grade>pass</grade></test><test><date>Fri Oct 14 01:57:02 KST 2005</date><file>level 0 writing.test</file><grade>pass</grade></test><test><date>Fri Nov 11 22:49:17 KST 2005</date><file>level 1 writing.test</file><grade>fail</grade></test><test><date>Mon Nov 28 16:52:36 KST 2005</date><file>level 1 reading.test</file><grade>fail</grade></test><test><date>Wed Nov 30 12:46:53 KST 2005</date><file>level 0 writing.test</file><grade>fail</grade></test><test><date>Tue Dec 27 11:50:09 KST 2005</date><file>level 0 writing.test</file><grade>fail</grade></test><test><date>Tue Dec 27 11:58:30 KST 2005</date><file>level 0 writing.test</file><grade>fail</grade></test><test><date>Tue Dec 27 22:39:38 KST 2005</date><file>level 0 writing.test</file><grade>fail</grade></test><test><date>Sun Jan 08 16:09:26 KST 2006</date><file>level 0 writing.test</file><grade>fail</grade></test><test><date>Fri Jan 13 13:08:06 KST 2006</date><file>level 0 reading.test</file><grade>pass</grade></test><test><date>Fri Jan 13 19:20:36 KST 2006</date><file>level 0 writing.test</file><grade>fail</grade></test><test><date>Tue Apr 18 19:14:50 KST 2006</date><file>level 1 reading.test</file><grade>fail</grade></test><test><date>Mon May 29 03:13:32 KST 2006</date><file>level 1 writing.test</file><grade>fail</grade></test><test><date>Tue Jun 06 21:25:09 KST 2006</date><file>level 0 reading.test</file><grade>pass</grade></test><test><date>Wed Oct 18 19:56:33 KST 2006</date><file>level 0 writing.test</file><grade>pass</grade></test><test><date>Wed Oct 25 19:42:50 KST 2006</date><file>level 1 writing.test</file><grade>fail</grade></test><test><date>Tue Oct 31 19:09:30 KST 2006</date><file>level 0 writing.test</file><grade>fail</grade></test><test><date>Sun Nov 12 15:34:29 KST 2006</date><file>level 1 reading.test</file><grade>pass</grade></test><test><date>Mon Nov 27 17:57:28 KST 2006</date><file>level 0 writing.test</file><grade>fail</grade></test><test><date>Fri Dec 15 19:48:27 KST 2006</date><file>level 0 writing.test</file><grade>fail</grade></test><test><date>Thu Jan 04 09:15:05 KST 2007</date><file>level 0 writing.test</file><grade>pass</grade></test><test><date>Wed Jun 13 01:03:20 KST 2007</date><file>level 2 reading.test</file><grade>pass</grade></test></word><word><text>다시아라봐</text><definition>Try to find out</definition><writing-level>2</writing-level><reading-level>3</reading-level><test><date>Fri Jan 28 08:19:00 PST 2005</date><file>level 0 writing.test</file><grade>fail</grade></test><test><date>Sun Jan 30 14:38:22 PST 2005</date><file>level 0 reading.test</file><grade>fail</grade></test><test><date>Wed Feb 02 21:09:01 PST 2005</date><file>level 0 writing.test</file><grade>pass</grade></test><test><date>Wed Mar 23 10:55:43 PST 2005</date><file>level 0 reading.test</file><grade>fail</grade></test><test><date>Tue Oct 04 12:47:00 KST 2005</date><file>level 0 reading.test</file><grade>pass</grade></test><test><date>Fri Nov 11 22:44:10 KST 2005</date><file>level 1 writing.test</file><grade>fail</grade></test><test><date>Mon Nov 28 16:52:36 KST 2005</date><file>level 1 reading.test</file><grade>pass</grade></test><test><date>Wed Nov 30 12:46:53 KST 2005</date><file>level 0 writing.test</file><grade>fail</grade></test><test><date>Tue Dec 27 11:50:09 KST 2005</date><file>level 0 writing.test</file><grade>fail</grade></test><test><date>Tue Dec 27 11:58:30 KST 2005</date><file>level 0 writing.test</file><grade>fail</grade></test><test><date>Tue Dec 27 22:39:38 KST 2005</date><file>level 0 writing.test</file><grade>fail</grade></test><test><date>Thu Dec 29 15:23:56 KST 2005</date><file>level 2 reading.test</file><grade>pass</grade></test><test><date>Sun Jan 08 16:09:26 KST 2006</date><file>level 0 writing.test</file><grade>fail</grade></test><test><date>Fri Jan 13 19:20:36 KST 2006</date><file>level 0 writing.test</file><grade>fail</grade></test><test><date>Sun Jan 15 14:06:52 KST 2006</date><file>level 0 writing.test</file><grade>fail</grade></test><test><date>Wed Feb 01 05:53:01 KST 2006</date><file>level 0 writing.test</file><grade>pass</grade></test><test><date>Mon May 29 03:11:47 KST 2006</date><file>level 1 writing.test</file><grade>fail</grade></test><test><date>Wed Aug 23 15:36:36 KST 2006</date><file>level 0 writing.test</file><grade>fail</grade></test><test><date>Wed Oct 18 19:52:42 KST 2006</date><file>level 0 writing.test</file><grade>fail</grade></test><test><date>Wed Oct 25 18:48:39 KST 2006</date><file>level 1 writing.test</file><grade>pass</grade></test></word><word><text>신나다</text><definition>To rejoice</definition><writing-level>1</writing-level><reading-level>1</reading-level><test><date>Fri Jan 28 08:19:00 PST 2005</date><file>level 0 writing.test</file><grade>pass</grade></test><test><date>Sun Jan 30 14:38:22 PST 2005</date><file>level 0 reading.test</file><grade>fail</grade></test><test><date>Wed Mar 23 10:55:43 PST 2005</date><file>level 0 reading.test</file><grade>fail</grade></test><test><date>Tue Oct 04 12:47:00 KST 2005</date><file>level 0 reading.test</file><grade>fail</grade></test><test><date>Tue Oct 04 18:00:09 KST 2005</date><file>level 0 reading.test</file><grade>fail</grade></test><test><date>Sun Oct 16 16:22:21 KST 2005</date><file>level 0 reading.test</file><grade>fail</grade></test><test><date>Sun Oct 16 16:24:23 KST 2005</date><file>level 0 reading.test</file><grade>fail</grade></test><test><date>Sun Oct 16 16:28:47 KST 2005</date><file>level 0 reading.test</file><grade>pass</grade></test><test><date>Fri Nov 11 22:44:10 KST 2005</date><file>level 1 writing.test</file><grade>pass</grade></test><test><date>Mon Nov 28 16:52:36 KST 2005</date><file>level 1 reading.test</file><grade>fail</grade></test><test><date>Mon Jan 09 03:52:01 KST 2006</date><file>level 2 writing.test</file><grade>fail</grade></test><test><date>Fri Jan 13 13:08:06 KST 2006</date><file>level 0 reading.test</file><grade>pass</grade></test><test><date>Tue Apr 18 19:12:40 KST 2006</date><file>level 1 reading.test</file><grade>fail</grade></test><test><date>Sat May 13 09:18:59 KST 2006</date><file>level 0 reading.test</file><grade>fail</grade></test><test><date>Mon May 29 03:11:47 KST 2006</date><file>level 1 writing.test</file><grade>fail</grade></test><test><date>Tue Jun 06 21:25:09 KST 2006</date><file>level 0 reading.test</file><grade>pass</grade></test><test><date>Wed Aug 23 15:36:36 KST 2006</date><file>level 0 writing.test</file><grade>fail</grade></test><test><date>Wed Oct 18 19:52:42 KST 2006</date><file>level 0 writing.test</file><grade>fail</grade></test><test><date>Wed Oct 18 19:55:02 KST 2006</date><file>level 0 writing.test</file><grade>pass</grade></test><test><date>Wed Oct 25 18:48:39 KST 2006</date><file>level 1 writing.test</file><grade>fail</grade></test><test><date>Tue Oct 31 19:07:31 KST 2006</date><file>level 0 writing.test</file><grade>fail</grade></test><test><date>Tue Oct 31 19:09:30 KST 2006</date><file>level 0 writing.test</file><grade>fail</grade></test><test><date>Sun Nov 12 15:34:29 KST 2006</date><file>level 1 reading.test</file><grade>pass</grade></test><test><date>Mon Nov 27 17:57:28 KST 2006</date><file>level 0 writing.test</file><grade>fail</grade></test><test><date>Fri Dec 15 19:48:27 KST 2006</date><file>level 0 writing.test</file><grade>pass</grade></test><test><date>Wed Jun 13 01:03:20 KST 2007</date><file>level 2 reading.test</file><grade>fail</grade></test></word><word><text>~그룻</text><definition>~bowls</definition><writing-level>3</writing-level><reading-level>3</reading-level><test><date>Fri Jan 28 08:19:00 PST 2005</date><file>level 0 writing.test</file><grade>fail</grade></test><test><date>Sun Jan 30 14:38:22 PST 2005</date><file>level 0 reading.test</file><grade>fail</grade></test><test><date>Wed Feb 02 21:15:19 PST 2005</date><file>level 0 writing.test</file><grade>fail</grade></test><test><date>Sun Feb 13 19:17:04 PST 2005</date><file>level 0 writing.test</file><grade>fail</grade></test><test><date>Sun Feb 13 19:25:00 PST 2005</date><file>level 0 writing.test</file><grade>pass</grade></test><test><date>Sat Mar 19 17:39:30 PST 2005</date><file>level 0 reading.test</file><grade>fail</grade></test><test><date>Sun Mar 20 22:14:18 PST 2005</date><file>level 1 writing.test</file><grade>fail</grade></test><test><date>Wed Mar 23 10:55:43 PST 2005</date><file>level 0 reading.test</file><grade>pass</grade></test><test><date>Fri Oct 14 01:57:02 KST 2005</date><file>level 0 writing.test</file><grade>pass</grade></test><test><date>Fri Nov 11 22:44:10 KST 2005</date><file>level 1 writing.test</file><grade>pass</grade></test><test><date>Mon Nov 28 16:52:36 KST 2005</date><file>level 1 reading.test</file><grade>pass</grade></test><test><date>Thu Dec 29 15:23:56 KST 2005</date><file>level 2 reading.test</file><grade>fail</grade></test><test><date>Mon Jan 09 03:52:01 KST 2006</date><file>level 2 writing.test</file><grade>pass</grade></test><test><date>Tue Apr 18 19:12:40 KST 2006</date><file>level 1 reading.test</file><grade>fail</grade></test><test><date>Tue Apr 18 19:14:50 KST 2006</date><file>level 1 reading.test</file><grade>pass</grade></test><test><date>Thu Jun 29 19:06:48 KST 2006</date><file>level 2 reading.test</file><grade>pass</grade></test></word><word><text>주인</text><definition>owner</definition><writing-level>3</writing-level><reading-level>3</reading-level><test><date>Fri Jan 28 08:19:00 PST 2005</date><file>level 0 writing.test</file><grade>pass</grade></test><test><date>Sun Jan 30 14:38:22 PST 2005</date><file>level 0 reading.test</file><grade>pass</grade></test><test><date>Sun Mar 20 22:14:18 PST 2005</date><file>level 1 writing.test</file><grade>pass</grade></test><test><date>Mon Nov 28 16:52:36 KST 2005</date><file>level 1 reading.test</file><grade>pass</grade></test><test><date>Thu Dec 29 15:23:56 KST 2005</date><file>level 2 reading.test</file><grade>pass</grade></test><test><date>Mon Jan 09 03:52:01 KST 2006</date><file>level 2 writing.test</file><grade>pass</grade></test></word><word><text>배달하다</text><definition>To deliver</definition><writing-level>3</writing-level><reading-level>3</reading-level><test><date>Fri Jan 28 08:19:00 PST 2005</date><file>level 0 writing.test</file><grade>pass</grade></test><test><date>Sun Jan 30 14:38:22 PST 2005</date><file>level 0 reading.test</file><grade>pass</grade></test><test><date>Sun Mar 20 22:14:18 PST 2005</date><file>level 1 writing.test</file><grade>pass</grade></test><test><date>Mon Nov 28 16:52:36 KST 2005</date><file>level 1 reading.test</file><grade>pass</grade></test><test><date>Thu Dec 29 15:23:56 KST 2005</date><file>level 2 reading.test</file><grade>pass</grade></test><test><date>Mon Jan 09 03:52:01 KST 2006</date><file>level 2 writing.test</file><grade>pass</grade></test></word>
</vocab>
